{"jobs": [
    {"company_name": "SAFT Bordeaux", 
    "person_role": "Ingenieure de surete de fonctionnement dans le secteur ferroviaire", 
    "title": "Definition d'un plan de surete conformement aux exigences client", 
    "start_date": "Septembre 2022", "end_date": "Present", "skills": ["Certification et evaluation", "Realiser les taches/ documentations techniques"], 
    "specification": "Realisation des dossiers de securite pour des batteries Ni-Cd/ Lithium"}, 
    {"company_name": "Ocado Engineering Paris", "person_role": "Ingenieure pilote de maintenance d'un entrepot robotise", 
    "title": "Maintenance reactive et preventive des robots mobiles", "start_date": "Fevrier 2020", "end_date": "Aout 2022", 
    "skills": ["Extraction et analyse de donnees pour de la maintenance preventive", "Responsable de l'organisation des formations HSE"], 
    "specification": ""}, 
    {"company_name": "Laboratoire PRISME Orleans", "person_role": "Ingenieure stagiaire en R &D", 
    "title": "Modelisation et controle predictif d'une combustion d'un moteur HCCI par ajout d'Ozone", "start_date": "Mars 2019", "end_date": "Novembre 2019", 
    "skills": ["Analyse, modelisation et identification des systemes non lineaires", "Conception d'une commande predictive"], 
    "specification": "Optimale et robuste sur Matlab/Simulink"}, 
    {"company_name": "OCP (Stage PFE)", "person_role": "", "title": "- Le dimensionnement d'une station de pompage", 
    "start_date": "Avril 2017", "end_date": "Juillet 2017", "skills": ["Reduire les couts necessaires des interventions"], "specification": ""}]}